zyb_image/__init__.py
zyb_image/image.py
zyb_image/assets/HYShangWeiXiaoShiHouJ.ttf
zyb_image-0.2.1.dist-info/LICENSE
zyb_image-0.2.1.dist-info/METADATA
zyb_image-0.2.1.dist-info/WHEEL
zyb_image-0.2.1.dist-info/top_level.txt
zyb_image-0.2.1.dist-info/RECORD
